README.txt
setup.cfg
setup.py
docs/HISTORY.txt
docs/INSTALL.txt
docs/LICENSE.GPL
docs/LICENSE.txt
rhizome/__init__.py
rhizome/interfaces.py
rhizome/store.py
rhizome/utils.py
rhizome.egg-info/PKG-INFO
rhizome.egg-info/SOURCES.txt
rhizome.egg-info/dependency_links.txt
rhizome.egg-info/entry_points.txt
rhizome.egg-info/namespace_packages.txt
rhizome.egg-info/not-zip-safe
rhizome.egg-info/requires.txt
rhizome.egg-info/top_level.txt
rhizome/five/README.txt
rhizome/five/__init__.py
rhizome/five/configure.zcml
rhizome/five/install.pt
rhizome/five/localsite.zcml
rhizome/five/site.py
rhizome/five/store.py
rhizome/five/tests.py
