Metadata-Version: 1.0
Name: rhizome
Version: 0.2.4
Summary: 'generalized rdf store for zope2 and zope3'
Home-page: http://openplans.org/projects/yucca
Author: whit
Author-email: whit@openplans.org
License: GPL
Keywords: zope2 zope3 rdf annotations yucca
Platform: UNKNOWN
